<?xml version="1.0" encoding="utf-8"?>
<docTables>
<docMetaData inputFile="102118188519MS.txt" extractionDate="2021-03-26T12:27:07Z">
<doi>10.2118/188519-MS</doi>
<pii>10.2118/188519-MS</pii>
<publisher>SPE_Society_of_Petroleum_Engineers</publisher>
</docMetaData>
<docFigureList>
<docFigure pdf-page="3" figure-order="1" data-type-order="2">
<link href="link-1" type="image" />
<appendix>
<linkTarget id="link-1" type="image">
<anchoringText id="Ancr2">Figures: 1, 2 and table 1 illustrate a geological overview of subject reservoir.</anchoringText>
<image-wrap id="102118188519MS-Img_SPi-1">
<label>Figure #1 </label>
<imageLink type="mediaResource" href="102118188519MS_i_1.tif" id="ImgLink-1" />
<caption>Layer X typical log</caption>
<formatted-caption>
<caption-label>Figure</caption-label>
<caption-order>#1</caption-order>
<caption-text>Layer X typical log</caption-text>
</formatted-caption>
</image-wrap>
</linkTarget>
</appendix>
</docFigure>
<docFigure pdf-page="3" figure-order="2" data-type-order="3">
<link href="link-2" type="image" />
<appendix>
<linkTarget id="link-2" type="image">
<anchoringText id="Ancr3">Figures: 1, 2 and table 1 illustrate a geological overview of subject reservoir.</anchoringText>
<image-wrap id="102118188519MS-Img_SPi-2">
<label>Figure #2 </label>
<imageLink type="mediaResource" href="102118188519MS_i_2.tif" id="ImgLink-2" />
<caption>General Structure overview</caption>
<formatted-caption>
<caption-label>Figure</caption-label>
<caption-order>#2</caption-order>
<caption-text>General Structure overview</caption-text>
</formatted-caption>
</image-wrap>
</linkTarget>
</appendix>
</docFigure>
<docFigure pdf-page="4" figure-order="3" data-type-order="4">
<link href="link-3" type="image" />
<appendix>
<linkTarget id="link-3" type="image">
<anchoringText id="Ancr4">Later in 1996, unsuccessful trial was made to revive the production from layer X1 through long string, in which a 2.31″ ‘FWG’ plug was set at the 2.31″ ‘F 'nipple and punched long string above the plug. In 2002 the wells was killed and secured with plugs. Since then water flooding had been advanced in reservoir X1 supported by water injection as demonstrated in following figure #3, 4 &amp; 5</anchoringText>
<image-wrap id="102118188519MS-Img_SPi-3">
<label>Figure #3 </label>
<imageLink type="mediaResource" href="102118188519MS_i_3.tif" id="ImgLink-3" />
<caption>"3 Phase saturation Map"</caption>
<formatted-caption>
<caption-label>Figure</caption-label>
<caption-order>#3</caption-order>
<caption-text>"3 Phase saturation Map"</caption-text>
</formatted-caption>
</image-wrap>
</linkTarget>
</appendix>
</docFigure>
<docFigure pdf-page="4" figure-order="4" data-type-order="5">
<link href="link-4" type="image" />
<appendix>
<linkTarget id="link-4" type="image">
<anchoringText id="Ancr5">Later in 1996, unsuccessful trial was made to revive the production from layer X1 through long string, in which a 2.31″ ‘FWG’ plug was set at the 2.31″ ‘F 'nipple and punched long string above the plug. In 2002 the wells was killed and secured with plugs. Since then water flooding had been advanced in reservoir X1 supported by water injection as demonstrated in following figure #3, 4 &amp; 5</anchoringText>
<image-wrap id="102118188519MS-Img_SPi-4">
<label>Figure #4 </label>
<imageLink type="mediaResource" href="102118188519MS_i_4.tif" id="ImgLink-4" />
<caption>Production Performance of well XX-01D</caption>
<formatted-caption>
<caption-label>Figure</caption-label>
<caption-order>#4</caption-order>
<caption-text>Production Performance of well XX-01D</caption-text>
</formatted-caption>
</image-wrap>
</linkTarget>
</appendix>
</docFigure>
<docFigure pdf-page="5" figure-order="5" data-type-order="6">
<link href="link-5" type="image" />
<appendix>
<linkTarget id="link-5" type="image">
<anchoringText id="Ancr6">Later in 1996, unsuccessful trial was made to revive the production from layer X1 through long string, in which a 2.31″ ‘FWG’ plug was set at the 2.31″ ‘F 'nipple and punched long string above the plug. In 2002 the wells was killed and secured with plugs. Since then water flooding had been advanced in reservoir X1 supported by water injection as demonstrated in following figure #3, 4 &amp; 5</anchoringText>
<image-wrap id="102118188519MS-Img_SPi-5">
<label>Figure #5 </label>
<imageLink type="mediaResource" href="102118188519MS_i_5.tif" id="ImgLink-5" />
<caption>old completion</caption>
<formatted-caption>
<caption-label>Figure</caption-label>
<caption-order>#5</caption-order>
<caption-text>old completion</caption-text>
</formatted-caption>
</image-wrap>
</linkTarget>
</appendix>
</docFigure>
<docFigure pdf-page="6" figure-order="6" data-type-order="7">
<link href="link-6" type="image" />
<appendix>
<linkTarget id="link-6" type="image">
<anchoringText id="Ancr7">Figure#6 provides the summary of reservoir evaluation for the subject well, where the simulation results show that the well is unable to produce when completed as normal deviated well.</anchoringText>
<image-wrap id="102118188519MS-Img_SPi-6">
<label>Figure #6 </label>
<imageLink type="mediaResource" href="102118188519MS_i_6.tif" id="ImgLink-6" />
<caption>"Reservoir Evaluation overview at the sidetrack feasible location"</caption>
<formatted-caption>
<caption-label>Figure</caption-label>
<caption-order>#6</caption-order>
<caption-text>"Reservoir Evaluation overview at the sidetrack feasible location"</caption-text>
</formatted-caption>
</image-wrap>
</linkTarget>
</appendix>
</docFigure>
<docFigure pdf-page="7" figure-order="7" data-type-order="8">
<link href="link-7" type="image" />
<appendix>
<linkTarget id="link-7" type="image">
<anchoringText id="Ancr8">Figure 7 &amp; 8 illustrated model water saturation along well trajectory for each completion case accomplished by well trajectory and model prediction results.</anchoringText>
<image-wrap id="102118188519MS-Img_SPi-7">
<label>Figure #7 </label>
<imageLink type="mediaResource" href="102118188519MS_i_7.tif" id="ImgLink-7" />
<caption>Model X-Cross section water saturation along the Planed Hz completion cases</caption>
<formatted-caption>
<caption-label>Figure</caption-label>
<caption-order>#7</caption-order>
<caption-text>Model X-Cross section water saturation along the Planed Hz completion cases</caption-text>
</formatted-caption>
</image-wrap>
</linkTarget>
</appendix>
</docFigure>
<docFigure pdf-page="7" figure-order="8" data-type-order="9">
<link href="link-8" type="image" />
<appendix>
<linkTarget id="link-8" type="image">
<anchoringText id="Ancr9">Figure 7 &amp; 8 illustrated model water saturation along well trajectory for each completion case accomplished by well trajectory and model prediction results.</anchoringText>
<image-wrap id="102118188519MS-Img_SPi-8">
<label>Figure #8 </label>
<imageLink type="mediaResource" href="102118188519MS_i_8.tif" id="ImgLink-8" />
<caption>simulation forecasts of four completion cases</caption>
<formatted-caption>
<caption-label>Figure</caption-label>
<caption-order>#8</caption-order>
<caption-text>simulation forecasts of four completion cases</caption-text>
</formatted-caption>
</image-wrap>
</linkTarget>
</appendix>
</docFigure>
<docFigure pdf-page="8" figure-order="9" data-type-order="10">
<link href="link-9" type="image" />
<appendix>
<linkTarget id="link-9" type="image">
<anchoringText id="Ancr10"> </anchoringText>
<image-wrap id="102118188519MS-Img_SPi-9">
<label>Figure #9 </label>
<imageLink type="mediaResource" href="102118188519MS_i_9.tif" id="ImgLink-9" />
<caption>"7" CSG Cement Evaluation Summary"</caption>
<formatted-caption>
<caption-label>Figure</caption-label>
<caption-order>#9</caption-order>
<caption-text>"7" CSG Cement Evaluation Summary"</caption-text>
</formatted-caption>
</image-wrap>
</linkTarget>
</appendix>
</docFigure>
<docFigure pdf-page="9" figure-order="10" data-type-order="11">
<link href="link-10" type="image" />
<appendix>
<linkTarget id="link-10" type="image">
<anchoringText id="Ancr11">It was believed that, this section was essentially against the dense zone, which separates the ADMA-OPCO reservoirs from the overlaying high pressure reservoirs. Moreover the presence of one hundred ft good cement below the deepest porous section was anticipated to act as a barrier between the two reservoirs, which would ultimately prevent flow behind casing as illustrated in below figure #10 &amp; 11.</anchoringText>
<image-wrap id="102118188519MS-Img_SPi-10">
<label>Figure #10 </label>
<imageLink type="mediaResource" href="102118188519MS_i_10.tif" id="ImgLink-10" />
<caption>Bottom 100 ft accessible of 7" CSG Cement Evaluation Section</caption>
<formatted-caption>
<caption-label>Figure</caption-label>
<caption-order>#10</caption-order>
<caption-text>Bottom 100 ft accessible of 7" CSG Cement Evaluation Section</caption-text>
</formatted-caption>
</image-wrap>
</linkTarget>
</appendix>
</docFigure>
<docFigure pdf-page="9" figure-order="11" data-type-order="12">
<link href="link-11" type="image" />
<appendix>
<linkTarget id="link-11" type="image">
<anchoringText id="Ancr12">It was believed that, this section was essentially against the dense zone, which separates the ADMA-OPCO reservoirs from the overlaying high pressure reservoirs. Moreover the presence of one hundred ft good cement below the deepest porous section was anticipated to act as a barrier between the two reservoirs, which would ultimately prevent flow behind casing as illustrated in below figure #10 &amp; 11.</anchoringText>
<image-wrap id="102118188519MS-Img_SPi-11">
<label>Figure #11 </label>
<imageLink type="mediaResource" href="102118188519MS_i_11.tif" id="ImgLink-11" />
<caption>Open Hole Log Interpretation of 6" pilot hole</caption>
<formatted-caption>
<caption-label>Figure</caption-label>
<caption-order>#11</caption-order>
<caption-text>Open Hole Log Interpretation of 6" pilot hole</caption-text>
</formatted-caption>
</image-wrap>
</linkTarget>
</appendix>
</docFigure>
<docFigure pdf-page="10" figure-order="12" data-type-order="13">
<link href="link-12" type="image" />
<appendix>
<linkTarget id="link-12" type="image">
<anchoringText id="Ancr13">Similar to the previous situation of 6" hole; WBT failed the negative test, where some leak was observed; however, positive test held good. All the effort spent to improve injectivity prior to remedial job was unsuccessful. The decision was taken to condition the mud weight to control the well and to complete the drilling of planned 2000 ft 6" horizontal drain at the top of reservoir only, as illustrated in figure #12. The most probably reason behind this situation was the presence of a localized porous section within the dense formation (isolating two reservoirs). This porous section is under appraisal phase.</anchoringText>
<image-wrap id="102118188519MS-Img_SPi-12">
<label>Figure #12 </label>
<imageLink type="mediaResource" href="102118188519MS_i_12.tif" id="ImgLink-12" />
<caption>Geosteering of 6" Hz drain</caption>
<formatted-caption>
<caption-label>Figure</caption-label>
<caption-order>#12</caption-order>
<caption-text>Geosteering of 6" Hz drain</caption-text>
</formatted-caption>
</image-wrap>
</linkTarget>
</appendix>
</docFigure>
<docFigure pdf-page="11" figure-order="13" data-type-order="14">
<link href="link-13" type="image" />
<appendix>
<linkTarget id="link-13" type="image">
<anchoringText id="Ancr14"> </anchoringText>
<image-wrap id="102118188519MS-Img_SPi-13">
<label>Figure #13 </label>
<imageLink type="mediaResource" href="102118188519MS_i_13.tif" id="ImgLink-13" />
<caption>Caliber log across 2000 ft of 6" Hz drain</caption>
<formatted-caption>
<caption-label>Figure</caption-label>
<caption-order>#13</caption-order>
<caption-text>Caliber log across 2000 ft of 6" Hz drain</caption-text>
</formatted-caption>
</image-wrap>
</linkTarget>
</appendix>
</docFigure>
<docFigure pdf-page="11" figure-order="14" data-type-order="15">
<link href="link-14" type="image" />
<appendix>
<linkTarget id="link-14" type="image">
<anchoringText id="Ancr15">The configuration of 4 1/2" liner and PKRs are illustarted in figures 14, 15 &amp; 16.</anchoringText>
<image-wrap id="102118188519MS-Img_SPi-14">
<label>Figure #14 </label>
<imageLink type="mediaResource" href="102118188519MS_i_14.tif" id="ImgLink-14" />
<caption>41/2" liner &amp; PKRs configuration</caption>
<formatted-caption>
<caption-label>Figure</caption-label>
<caption-order>#14</caption-order>
<caption-text>41/2" liner &amp; PKRs configuration</caption-text>
</formatted-caption>
</image-wrap>
</linkTarget>
</appendix>
</docFigure>
<docFigure pdf-page="12" figure-order="15" data-type-order="16">
<link href="link-15" type="image" />
<appendix>
<linkTarget id="link-15" type="image">
<anchoringText id="Ancr16">The configuration of 4 1/2" liner and PKRs are illustarted in figures 14, 15 &amp; 16.</anchoringText>
<image-wrap id="102118188519MS-Img_SPi-15">
<label>Figure #15 </label>
<imageLink type="mediaResource" href="102118188519MS_i_15.tif" id="ImgLink-15" />
<caption>Casing Sketch</caption>
<formatted-caption>
<caption-label>Figure</caption-label>
<caption-order>#15</caption-order>
<caption-text>Casing Sketch</caption-text>
</formatted-caption>
</image-wrap>
</linkTarget>
</appendix>
</docFigure>
<docFigure pdf-page="13" figure-order="16" data-type-order="17">
<link href="link-16" type="image" />
<appendix>
<linkTarget id="link-16" type="image">
<anchoringText id="Ancr17">The configuration of 4 1/2" liner and PKRs are illustarted in figures 14, 15 &amp; 16.</anchoringText>
<image-wrap id="102118188519MS-Img_SPi-16">
<label>Figure #16 </label>
<imageLink type="mediaResource" href="102118188519MS_i_16.tif" id="ImgLink-16" />
<caption>Completion Description</caption>
<formatted-caption>
<caption-label>Figure</caption-label>
<caption-order>#16</caption-order>
<caption-text>Completion Description</caption-text>
</formatted-caption>
</image-wrap>
</linkTarget>
</appendix>
</docFigure>
<docFigure pdf-page="14" figure-order="17" data-type-order="18">
<link href="link-17" type="image" />
<appendix>
<linkTarget id="link-17" type="image">
<anchoringText id="Ancr18">The well has been online successfully after post rig stimulation with healthy oil i.e. no WC and normal associated GOR. Both, the production data and the bottom hole pressure survey confirmed the integrity of 41/2" liner i.e. no inter reservoir communication from the overlaying pressurized reservoir. Figures 17 &amp; 18 illustrated production performance and reservoir pressure bubble map of offset wells producing from layer "X1".</anchoringText>
<image-wrap id="102118188519MS-Img_SPi-17">
<label>Figure #17 </label>
<imageLink type="mediaResource" href="102118188519MS_i_17.tif" id="ImgLink-17" />
<caption>production performance of well XX-03H</caption>
<formatted-caption>
<caption-label>Figure</caption-label>
<caption-order>#17</caption-order>
<caption-text>production performance of well XX-03H</caption-text>
</formatted-caption>
</image-wrap>
</linkTarget>
</appendix>
</docFigure>
<docFigure pdf-page="14" figure-order="18" data-type-order="19">
<link href="link-18" type="image" />
<appendix>
<linkTarget id="link-18" type="image">
<anchoringText id="Ancr19">The well has been online successfully after post rig stimulation with healthy oil i.e. no WC and normal associated GOR. Both, the production data and the bottom hole pressure survey confirmed the integrity of 41/2" liner i.e. no inter reservoir communication from the overlaying pressurized reservoir. Figures 17 &amp; 18 illustrated production performance and reservoir pressure bubble map of offset wells producing from layer "X1".</anchoringText>
<image-wrap id="102118188519MS-Img_SPi-18">
<label>Figure #18 </label>
<imageLink type="mediaResource" href="102118188519MS_i_18.tif" id="ImgLink-18" />
<caption>Layer "X1" Press bubble map</caption>
<formatted-caption>
<caption-label>Figure</caption-label>
<caption-order>#18</caption-order>
<caption-text>Layer "X1" Press bubble map</caption-text>
</formatted-caption>
</image-wrap>
</linkTarget>
</appendix>
</docFigure>
</docFigureList>
</docTables>