<?xml version="1.0" encoding="utf-8"?>
<docTables>
<docMetaData inputFile="102118191248MS.txt" extractionDate="2021-03-29T14:47:36Z">
<doi>10.2118/191248-MS</doi>
<pii>10.2118/191248-MS</pii>
<publisher>SPE_Society_of_Petroleum_Engineers</publisher>
</docMetaData>
<docFigureList>
<docFigure pdf-page="2" figure-order="1" data-type-order="1">
<link href="link-1" type="image" />
<appendix>
<linkTarget id="link-1" type="image">
<anchoringText id="Ancr2"> </anchoringText>
<image-wrap id="102118191248MS-Img_SPi-1">
<label>Figure 1 </label>
<imageLink type="mediaResource" href="102118191248MS_i_1.tif" id="ImgLink-1" />
<caption>The Drago Complex field development</caption>
<formatted-caption>
<caption-label>Figure</caption-label>
<caption-order>1</caption-order>
<caption-text>The Drago Complex field development</caption-text>
</formatted-caption>
</image-wrap>
</linkTarget>
</appendix>
</docFigure>
<docFigure pdf-page="3" figure-order="2" data-type-order="2">
<link href="link-2" type="image" />
<appendix>
<linkTarget id="link-2" type="image">
<anchoringText id="Ancr3">It is the product of the reactivation of pre-Cretaceous faults, transient movements and the intrusion of igneous bodies, which in conjunction gave the genesis to this geological structure. Located in the foredeep of the Oriente Basin with coastal and transitional delta and estuary deposits. The Drago Complex is an elongated anticline with preferential direction N-S product of compressive stresses. The main reservoirs are the U and T sandstones, Fig.2.</anchoringText>
<image-wrap id="102118191248MS-Img_SPi-2">
<label>Figure 2 </label>
<imageLink type="mediaResource" href="102118191248MS_i_2.tif" id="ImgLink-2" />
<caption>Structural correlation showing main reservoirs</caption>
<formatted-caption>
<caption-label>Figure</caption-label>
<caption-order>2</caption-order>
<caption-text>Structural correlation showing main reservoirs</caption-text>
</formatted-caption>
</image-wrap>
</linkTarget>
</appendix>
</docFigure>
<docFigure pdf-page="3" figure-order="3" data-type-order="3">
<link href="link-3" type="image" />
<appendix>
<linkTarget id="link-3" type="image">
<anchoringText id="Ancr4">The accuracy of the study can only be proved by the performance of the wells once the jobs are executed. During the development of the Drago Complex, a great amount of information was collected to characterize the different reservoirs. With this great amount of data collected over the years, a known methodology was applied using the corporate software to collect, organize, standardize and turn data into information as shown in Fig. 3, (Consentino, 2001). Once the information was organized and structured, a comprehensive workflow was used to define the opportunities of incremental oil production, (Ruano, 2014).</anchoringText>
<image-wrap id="102118191248MS-Img_SPi-3">
<label>Figure 3 </label>
<imageLink type="mediaResource" href="102118191248MS_i_3.tif" id="ImgLink-3" />
<caption>Ideal Structure of a project database (Consentino, 2001)</caption>
<formatted-caption>
<caption-label>Figure</caption-label>
<caption-order>3</caption-order>
<caption-text>Ideal Structure of a project database (<link href="BIB1">Consentino, 2001</link>)</caption-text>
</formatted-caption>
</image-wrap>
</linkTarget>
<linkTarget id="link-26" type="bib">
<bib id="BIB1">
<label>Consentino, 2001</label>
<author>
<first-name>L.</first-name>
<last-name>Consentino</last-name>
</author>
<pubDate>2001</pubDate>, <i>The Integrated Database, In Integrated Reservoir Studies</i>, First edition, Chap. 2, <pages>
<first-page>20</first-page>
</pages>, Paris France: Editions TECHNIP.</bib>
</linkTarget>
</appendix>
</docFigure>
<docFigure pdf-page="4" figure-order="4" data-type-order="4">
<link href="link-4" type="image" />
<appendix>
<linkTarget id="link-4" type="image">
<anchoringText id="Ancr5">The application of PTA on this study was focused on production engineering i.e. the individual well (Spivey, 2013). Various tests were evaluated on each well to obtain quantitative updated values of permeability, skin and reservoir pressure. The methodology used is described by Izurieta (2015). Results from this evaluation showed that most wells in the field had a high skin, which was not deep enough to be removed with conventional approaches such as re-perforating or matrix acidizing, Fig. 4,therefore a more appropriate remedial or stimulation technique must be used (Spivey, 2013).</anchoringText>
<image-wrap id="102118191248MS-Img_SPi-4">
<label>Figure 4 </label>
<imageLink type="mediaResource" href="102118191248MS_i_4.tif" id="ImgLink-4" />
<caption>Updated petrophysical interpretation and global hydraulic elements</caption>
<formatted-caption>
<caption-label>Figure</caption-label>
<caption-order>4</caption-order>
<caption-text>Updated petrophysical interpretation and global hydraulic elements</caption-text>
</formatted-caption>
</image-wrap>
</linkTarget>
</appendix>
</docFigure>
<docFigure pdf-page="4" figure-order="5" data-type-order="5">
<link href="link-5" type="image" />
<appendix>
<linkTarget id="link-5" type="image">
<anchoringText id="Ancr6">The next step on the workflow was to review well log data, both open hole and cased hole. To achieve this goal all conventional and nuclear magnetic resonance (NMR) logs were loaded in the corporate database. Logs were environmentally corrected, well tops updated and petrophysical evaluation was calibrated with core data (Bateman, 2012). The permeability was derived from methodologies like Winland R35 or global hydraulic elements (Corbett, 2007). Along with NMR, carbon/oxygen logs and this updated interpretation, new pay zones and additional pay intervals on known reservoirs were identified as shown in Fig. 5.</anchoringText>
<image-wrap id="102118191248MS-Img_SPi-5">
<label>Figure 5 </label>
<imageLink type="mediaResource" href="102118191248MS_i_5.tif" id="ImgLink-5" />
<caption>Updated petrophysical interpretation and global hydraulic elements</caption>
<formatted-caption>
<caption-label>Figure</caption-label>
<caption-order>5</caption-order>
<caption-text>Updated petrophysical interpretation and global hydraulic elements</caption-text>
</formatted-caption>
</image-wrap>
</linkTarget>
</appendix>
</docFigure>
<docFigure pdf-page="6" figure-order="6" data-type-order="6">
<link href="link-6" type="image" />
<appendix>
<linkTarget id="link-6" type="image">
<anchoringText id="Ancr7">Because of the deep penetrating nature of the damaged region present on the studied wells, hydraulic fracturing was selected as the appropriate technique to restore well productivity. The production optimization workflow as shown in Fig.6, (Ghalambor, 2009) is found in the following way:</anchoringText>
<image-wrap id="102118191248MS-Img_SPi-6">
<label>Figure 6 </label>
<imageLink type="mediaResource" href="102118191248MS_i_6.tif" id="ImgLink-6" />
<caption>Production Optimization Workflow</caption>
<formatted-caption>
<caption-label>Figure</caption-label>
<caption-order>6</caption-order>
<caption-text>Production Optimization Workflow</caption-text>
</formatted-caption>
</image-wrap>
</linkTarget>
</appendix>
</docFigure>
<docFigure pdf-page="7" figure-order="7" data-type-order="7">
<link href="link-7" type="image" />
<appendix>
<linkTarget id="link-7" type="image">
<anchoringText id="Ancr8">The next step in this process was to determine the dimension of the fracture half-length needed, based on permeability values derived from PTA. The approach from Gidley, (1990), Fig.7, was selected and by using permeability data, the maximum fracture half-length was limited to xf≈250 ft.</anchoringText>
<image-wrap id="102118191248MS-Img_SPi-7">
<label>Figure 7 </label>
<imageLink type="mediaResource" href="102118191248MS_i_7.tif" id="ImgLink-7" />
<caption>Desired fracture half lengths for different formation permeabilities (Modified after Gidley, 1990)</caption>
<formatted-caption>
<caption-label>Figure</caption-label>
<caption-order>7</caption-order>
<caption-text>Desired fracture half lengths for different formation permeabilities (Modified after Gidley, 1990)</caption-text>
</formatted-caption>
</image-wrap>
</linkTarget>
</appendix>
</docFigure>
<docFigure pdf-page="7" figure-order="8" data-type-order="8">
<link href="link-8" type="image" />
<appendix>
<linkTarget id="link-8" type="image">
<anchoringText id="Ancr9">Tip Screen Out (TSO). Based on the permeability range, the TSO technique was selected as the appropriate design to reach the productivity goals. This technique relies on propped fracture width as the key component to generate fracture conductivity, this is achieved by a rapid increase in proppant concentration, Fig. 8,(Jones, 2009). A sample of the net pressure behavior observed on these jobs is shown on the Nolte-Smith plot, Fig.9.</anchoringText>
<image-wrap id="102118191248MS-Img_SPi-8">
<label>Figure 8 </label>
<imageLink type="mediaResource" href="102118191248MS_i_8.tif" id="ImgLink-8" />
<caption>Conceptual design of TSO treatment and actual treatment (Modified after Jones, 2009)</caption>
<formatted-caption>
<caption-label>Figure</caption-label>
<caption-order>8</caption-order>
<caption-text>Conceptual design of TSO treatment and actual treatment (Modified after Jones, 2009)</caption-text>
</formatted-caption>
</image-wrap>
</linkTarget>
</appendix>
</docFigure>
<docFigure pdf-page="8" figure-order="9" data-type-order="9">
<link href="link-9" type="image" />
<appendix>
<linkTarget id="link-9" type="image">
<anchoringText id="Ancr10">Tip Screen Out (TSO). Based on the permeability range, the TSO technique was selected as the appropriate design to reach the productivity goals. This technique relies on propped fracture width as the key component to generate fracture conductivity, this is achieved by a rapid increase in proppant concentration, Fig. 8,(Jones, 2009). A sample of the net pressure behavior observed on these jobs is shown on the Nolte-Smith plot, Fig.9.</anchoringText>
<image-wrap id="102118191248MS-Img_SPi-9">
<label>Figure 9 </label>
<imageLink type="mediaResource" href="102118191248MS_i_9.tif" id="ImgLink-9" />
<caption>Net pressure behavior of TSO treatment</caption>
<formatted-caption>
<caption-label>Figure</caption-label>
<caption-order>9</caption-order>
<caption-text>Net pressure behavior of TSO treatment</caption-text>
</formatted-caption>
</image-wrap>
</linkTarget>
</appendix>
</docFigure>
<docFigure pdf-page="8" figure-order="10" data-type-order="10">
<link href="link-10" type="image" />
<appendix>
<linkTarget id="link-10" type="image">
<anchoringText id="Ancr11">By using the classification described by Economides (2000), Fig.10, the typical drainage volumes found in the Drago Complex were selected. The usual workover jobs performed on each type of drainage area were also outlined and the expected fracture design was adjusted based on the following reservoir characteristics:</anchoringText>
<image-wrap id="102118191248MS-Img_SPi-10">
<label>Figure 10 </label>
<imageLink type="mediaResource" href="102118191248MS_i_10.tif" id="ImgLink-10" />
<caption>Drago Complex, Drainage Volume Characterization (Modified after Economides, 2000)</caption>
<formatted-caption>
<caption-label>Figure</caption-label>
<caption-order>10</caption-order>
<caption-text>Drago Complex, Drainage Volume Characterization (Modified after <link href="BIB2">Economides, 2000</link>)</caption-text>
</formatted-caption>
</image-wrap>
</linkTarget>
<linkTarget id="link-27" type="bib">
<bib id="BIB2">
<label>Economides and Nolte, 2000</label>
<author>
<first-name>M.</first-name>
<last-name>Economides</last-name>
</author>, <author>
<first-name>K.</first-name>
<last-name>Nolte</last-name>
</author>, <pubDate>2000</pubDate>, <i>Reservoir Stimulation in Petroleum Production, In Reservoir Stimulation</i>, Third edition, Chap. 1, <pages>
<first-page>25</first-page>
</pages>, West Sussex, England: John Wiley &amp; Sons.</bib>
</linkTarget>
</appendix>
</docFigure>
<docFigure pdf-page="10" figure-order="11" data-type-order="12">
<link href="link-11" type="image" />
<appendix>
<linkTarget id="link-11" type="image">
<anchoringText id="Ancr12">To complement the production calculations and to have an idea of the artificial lift needed, the study included nodal analysis (Inflow performance relationship + vertical flow performance), Fig. 11. Sensitivities to equivalent radial fracture skin and to the artificial lift equipment -number of stages, frequency and intake depth- were performed to define the expected production with the definitive completion.</anchoringText>
<image-wrap id="102118191248MS-Img_SPi-11">
<label>Figure 11 </label>
<imageLink type="mediaResource" href="102118191248MS_i_11.tif" id="ImgLink-11" />
<caption>Complete nodal analysis including artificial lift</caption>
<formatted-caption>
<caption-label>Figure</caption-label>
<caption-order>11</caption-order>
<caption-text>Complete nodal analysis including artificial lift</caption-text>
</formatted-caption>
</image-wrap>
</linkTarget>
</appendix>
</docFigure>
<docFigure pdf-page="10" figure-order="12" data-type-order="13">
<link href="link-12" type="image" />
<appendix>
<linkTarget id="link-12" type="image">
<anchoringText id="Ancr13">The decision tree shown in Fig. 12 highlights the possible scenarios during workover planning that helped to maximize NPV. This project used historical information and aimed to take new information to evaluate the productivity increase in each case, i.e. value of information, (Kamal, 2009). In some cases, the information showed a high risk for the project, at this point the asset team had the possibility to make an informed decision as to whether the project should bedropped or the workover should be re-designed according to the new data and if the risk was still favorable to production, the project should continue.</anchoringText>
<image-wrap id="102118191248MS-Img_SPi-12">
<label>Figure 12 </label>
<imageLink type="mediaResource" href="102118191248MS_i_12.tif" id="ImgLink-12" />
<caption>NPV maximization though informed decisions and decision tree (Modified after Kamal, 2009)</caption>
<formatted-caption>
<caption-label>Figure</caption-label>
<caption-order>12</caption-order>
<caption-text>NPV maximization though informed decisions and decision tree (Modified after <link href="BIB3">Kamal, 2009</link>)</caption-text>
</formatted-caption>
</image-wrap>
</linkTarget>
<linkTarget id="link-28" type="bib">
<bib id="BIB3">
<label>Kamal, 2009</label>
<author>
<first-name>M.</first-name>
<last-name>Kamal</last-name>
</author>, <pubDate>2009</pubDate>, <i>Transient Well Testing</i>, First edition, <pages>
<first-page>53</first-page>
<last-page>67</last-page>
</pages>, Richardson, Texas: Monograph Series, SPE.</bib>
</linkTarget>
</appendix>
</docFigure>
<docFigure pdf-page="11" figure-order="13" data-type-order="14">
<link href="link-13" type="image" />
<appendix>
<linkTarget id="link-13" type="image">
<anchoringText id="Ancr14">The project started with one rig performing the early positive results which confirmed that production potential from productivity assessments were in the expected range. Later on, two followed by three rigs were active on the field. Oncemost of the jobs were executed, two rigs demobilized and only one rig remained active on the field, Fig. 13. The highlights of this work are next described:</anchoringText>
<image-wrap id="102118191248MS-Img_SPi-13">
<label>Figure 13 </label>
<imageLink type="mediaResource" href="102118191248MS_i_13.tif" id="ImgLink-13" />
<caption>Fractures vs Time</caption>
<formatted-caption>
<caption-label>Figure</caption-label>
<caption-order>13</caption-order>
<caption-text>Fractures vs Time</caption-text>
</formatted-caption>
</image-wrap>
</linkTarget>
</appendix>
</docFigure>
<docFigure pdf-page="12" figure-order="14" data-type-order="15">
<link href="link-14" type="image" />
<appendix>
<linkTarget id="link-14" type="image">
<anchoringText id="Ancr15">Incremental oil production of 12,948 Stb/day as December 2017, Fig. 14.</anchoringText>
<image-wrap id="102118191248MS-Img_SPi-14">
<label>Figure 14 </label>
<imageLink type="mediaResource" href="102118191248MS_i_14.tif" id="ImgLink-14" />
<caption>Fractures vs Time</caption>
<formatted-caption>
<caption-label>Figure</caption-label>
<caption-order>14</caption-order>
<caption-text>Fractures vs Time</caption-text>
</formatted-caption>
</image-wrap>
</linkTarget>
</appendix>
</docFigure>
<docFigure pdf-page="12" figure-order="15" data-type-order="16">
<link href="link-15" type="image" />
<appendix>
<linkTarget id="link-15" type="image">
<anchoringText id="Ancr16">Initially, a top producer on the field was 600 Stb/d in December 2016, by hydraulic fracturing the top producer reached 2,000 Stb/d, with an average of 563 stb/d per fractured well (this average includes wells that did not produce after fracture operations for differing reasons). Fig. 15, shows a monthly bubble map, where red bubbles shows wells with production &#x003E; = 600 Stb/d. The graphs start on January 2017 on the top left, moving to the right and finishing on December 2017. At the end of 2017, most wells on the field surpassed the 600 stb/d.</anchoringText>
<image-wrap id="102118191248MS-Img_SPi-15">
<label>Figure 15 </label>
<imageLink type="mediaResource" href="102118191248MS_i_15.tif" id="ImgLink-15" />
<caption>Bubble map, average monthly oil rate, Drago Complex</caption>
<formatted-caption>
<caption-label>Figure</caption-label>
<caption-order>15</caption-order>
<caption-text>Bubble map, average monthly oil rate, Drago Complex</caption-text>
</formatted-caption>
</image-wrap>
</linkTarget>
</appendix>
</docFigure>
<docFigure pdf-page="13" figure-order="16" data-type-order="17">
<link href="link-16" type="image" />
<appendix>
<linkTarget id="link-16" type="image">
<anchoringText id="Ancr17">The well Drago Norte-015, which had the highest oil production of the field, not only became the best oil producer from the Drago Complex but also remained as one of the top ten producers from Ecuador's NOC which accounts for the 80% of the national oil production, Fig.16.</anchoringText>
<image-wrap id="102118191248MS-Img_SPi-16">
<label>Figure 16 </label>
<imageLink type="mediaResource" href="102118191248MS_i_16.tif" id="ImgLink-16" />
<caption>Ecuador NOC, Top Ten producers as February 2018</caption>
<formatted-caption>
<caption-label>Figure</caption-label>
<caption-order>16</caption-order>
<caption-text>Ecuador NOC, Top Ten producers as February 2018</caption-text>
</formatted-caption>
</image-wrap>
</linkTarget>
</appendix>
</docFigure>
<docFigure pdf-page="14" figure-order="17" data-type-order="18">
<link href="link-17" type="image" />
<appendix>
<linkTarget id="link-17" type="image">
<anchoringText id="Ancr18">The pressure recorded in most of the wells after hydraulic fracturing confirmed the overall good results showing negative skins in most cases, Fig. 17. Results from this interpretation were also used to design the definitive artificial lift equipment to be installed.</anchoringText>
<image-wrap id="102118191248MS-Img_SPi-17">
<label>Figure 17 </label>
<imageLink type="mediaResource" href="102118191248MS_i_17.tif" id="ImgLink-17" />
<caption>Skin factor before and after hydraulic fracturing</caption>
<formatted-caption>
<caption-label>Figure</caption-label>
<caption-order>17</caption-order>
<caption-text>Skin factor before and after hydraulic fracturing</caption-text>
</formatted-caption>
</image-wrap>
</linkTarget>
</appendix>
</docFigure>
<docFigure pdf-page="14" figure-order="18" data-type-order="19">
<link href="link-18" type="image" />
<appendix>
<linkTarget id="link-18" type="image">
<anchoringText id="Ancr19">In terms of complexity, three main types of fractures were executed, as described in the drainage area characterization. The most productive wells resulted from TSO operations performed in layers with and without water contact. As the complexity increased, so did fracture dimensions and proppant mass, also, the investment needed was higher because of lower permeability reservoirs, Fig.18.</anchoringText>
<image-wrap id="102118191248MS-Img_SPi-18">
<label>Figure 18 </label>
<imageLink type="mediaResource" href="102118191248MS_i_18.tif" id="ImgLink-18" />
<caption>Learning curve</caption>
<formatted-caption>
<caption-label>Figure</caption-label>
<caption-order>18</caption-order>
<caption-text>Learning curve</caption-text>
</formatted-caption>
</image-wrap>
</linkTarget>
</appendix>
</docFigure>
<docFigure pdf-page="15" figure-order="19" data-type-order="20">
<link href="link-19" type="image" />
<appendix>
<linkTarget id="link-19" type="image">
<anchoringText id="Ancr20">Results from this evaluation, Fig. 19, showed that the project recovered the investment approximately at the third month of execution.</anchoringText>
<image-wrap id="102118191248MS-Img_SPi-19">
<label>Figure 19 </label>
<imageLink type="mediaResource" href="102118191248MS_i_19.tif" id="ImgLink-19" />
<caption>Net Revenue vs Time</caption>
<formatted-caption>
<caption-label>Figure</caption-label>
<caption-order>19</caption-order>
<caption-text>Net Revenue vs Time</caption-text>
</formatted-caption>
</image-wrap>
</linkTarget>
</appendix>
</docFigure>
<docFigure pdf-page="16" figure-order="20" data-type-order="21">
<link href="link-20" type="image" />
<appendix>
<linkTarget id="link-20" type="image">
<anchoringText id="Ancr21">From the PTA update a skin of 19.7 was calculated and from fracture design a FOI = 8.5 was estimated. The job consisted of 13,400 pounds of proppant 20/40 in the Lower U sandstone using the TSO technique, Fig. 20. The production increased to 600 STB/d with a skin of −3.7. The fracturing pressure, rate and proppant concentration is shown in Fig.20, the production profile before and after the fracture is shown in Fig.21.</anchoringText>
<image-wrap id="102118191248MS-Img_SPi-20">
<label>Figure 20 </label>
<imageLink type="mediaResource" href="102118191248MS_i_20.tif" id="ImgLink-20" />
<caption>Case study 1, fracture job</caption>
<formatted-caption>
<caption-label>Figure</caption-label>
<caption-order>20</caption-order>
<caption-text>Case study 1, fracture job</caption-text>
</formatted-caption>
</image-wrap>
</linkTarget>
</appendix>
</docFigure>
<docFigure pdf-page="16" figure-order="21" data-type-order="22">
<link href="link-21" type="image" />
<appendix>
<linkTarget id="link-21" type="image">
<anchoringText id="Ancr22">From the PTA update a skin of 19.7 was calculated and from fracture design a FOI = 8.5 was estimated. The job consisted of 13,400 pounds of proppant 20/40 in the Lower U sandstone using the TSO technique, Fig. 20. The production increased to 600 STB/d with a skin of −3.7. The fracturing pressure, rate and proppant concentration is shown in Fig.20, the production profile before and after the fracture is shown in Fig.21.</anchoringText>
<image-wrap id="102118191248MS-Img_SPi-21">
<label>Figure 21 </label>
<imageLink type="mediaResource" href="102118191248MS_i_21.tif" id="ImgLink-21" />
<caption>Case study 1, historical production</caption>
<formatted-caption>
<caption-label>Figure</caption-label>
<caption-order>21</caption-order>
<caption-text>Case study 1, historical production</caption-text>
</formatted-caption>
</image-wrap>
</linkTarget>
</appendix>
</docFigure>
<docFigure pdf-page="17" figure-order="22" data-type-order="23">
<link href="link-22" type="image" />
<appendix>
<linkTarget id="link-22" type="image">
<anchoringText id="Ancr23">Due to the relative high water cut, a small fracture was planned and executed, which consisted of 12,450 pounds of proppant 20/40 in the Main T Sandstone. The oil production increased to 1,000 SBT/d with 40% water cut and a skin of −2.5. The fracturing pressure, rate and proppant concentration is shown in Fig.22. The production profile before and after the fracture is shown in Fig.23.</anchoringText>
<image-wrap id="102118191248MS-Img_SPi-22">
<label>Figure 22 </label>
<imageLink type="mediaResource" href="102118191248MS_i_22.tif" id="ImgLink-22" />
<caption>Case study 2, fracture job</caption>
<formatted-caption>
<caption-label>Figure</caption-label>
<caption-order>22</caption-order>
<caption-text>Case study 2, fracture job</caption-text>
</formatted-caption>
</image-wrap>
</linkTarget>
</appendix>
</docFigure>
<docFigure pdf-page="17" figure-order="23" data-type-order="24">
<link href="link-23" type="image" />
<appendix>
<linkTarget id="link-23" type="image">
<anchoringText id="Ancr24">Due to the relative high water cut, a small fracture was planned and executed, which consisted of 12,450 pounds of proppant 20/40 in the Main T Sandstone. The oil production increased to 1,000 SBT/d with 40% water cut and a skin of −2.5. The fracturing pressure, rate and proppant concentration is shown in Fig.22. The production profile before and after the fracture is shown in Fig.23.</anchoringText>
<image-wrap id="102118191248MS-Img_SPi-23">
<label>Figure 23 </label>
<imageLink type="mediaResource" href="102118191248MS_i_23.tif" id="ImgLink-23" />
<caption>Case study 2, historical production</caption>
<formatted-caption>
<caption-label>Figure</caption-label>
<caption-order>23</caption-order>
<caption-text>Case study 2, historical production</caption-text>
</formatted-caption>
</image-wrap>
</linkTarget>
</appendix>
</docFigure>
<docFigure pdf-page="18" figure-order="24" data-type-order="25">
<link href="link-24" type="image" />
<appendix>
<linkTarget id="link-24" type="image">
<anchoringText id="Ancr25">This well was active before the fracture job with an oil production of 250 STB/d. From the PTA update, a skin of 13.95 was calculated and from fracture design, a FOI = 4.8 was estimated. The job consisted on 13,200 pounds of proppant 20/40 in the Lower U sandstone using the TSO technique, Fig. 22. The production increased to 2,000 STB/d with a skin of −2.15. The fracturing pressure, rate and proppant concentration is shown in Fig.24, the production profile before and after the fracture is shown in Fig.25.</anchoringText>
<image-wrap id="102118191248MS-Img_SPi-24">
<label>Figure 24 </label>
<imageLink type="mediaResource" href="102118191248MS_i_24.tif" id="ImgLink-24" />
<caption>Case study 2, fracture job</caption>
<formatted-caption>
<caption-label>Figure</caption-label>
<caption-order>24</caption-order>
<caption-text>Case study 2, fracture job</caption-text>
</formatted-caption>
</image-wrap>
</linkTarget>
</appendix>
</docFigure>
<docFigure pdf-page="18" figure-order="25" data-type-order="26">
<link href="link-25" type="image" />
<appendix>
<linkTarget id="link-25" type="image">
<anchoringText id="Ancr26">This well was active before the fracture job with an oil production of 250 STB/d. From the PTA update, a skin of 13.95 was calculated and from fracture design, a FOI = 4.8 was estimated. The job consisted on 13,200 pounds of proppant 20/40 in the Lower U sandstone using the TSO technique, Fig. 22. The production increased to 2,000 STB/d with a skin of −2.15. The fracturing pressure, rate and proppant concentration is shown in Fig.24, the production profile before and after the fracture is shown in Fig.25.</anchoringText>
<image-wrap id="102118191248MS-Img_SPi-25">
<label>Figure 25 </label>
<imageLink type="mediaResource" href="102118191248MS_i_25.tif" id="ImgLink-25" />
<caption>Case study 3, historical production</caption>
<formatted-caption>
<caption-label>Figure</caption-label>
<caption-order>25</caption-order>
<caption-text>Case study 3, historical production</caption-text>
</formatted-caption>
</image-wrap>
</linkTarget>
</appendix>
</docFigure>
</docFigureList>
</docTables>